{
  "name": "神州战役卡牌包",
  "version": "1.3.0",
  "description": "一个以中国神话和东方奇幻为灵感的中式战役框架，由Tiger设计。包含神州大陆独特的族裔与地理出身，为你的《匕首之心》冒险带来浓郁的东方意蕴。",
  "author": "Tiger <1322509073@qq.com>",
  "customFieldDefinitions": {
    "variantTypes": {},
    "professions": [],
    "ancestries": [
      "械灵",
      "龙人",
      "矮人",
      "精灵",
      "羽灵",
      "狐族",
      "熊猫裔",
      "木灵",
      "龟人",
      "巨人",
      "蛇人",
      "半身人",
      "人类",
      "魔裔",
      "虎族",
      "獠族",
      "蛙裔",
      "猿族"
    ],
    "communities": [
      "中州出身",
      "苍岭出身",
      "丹泽出身",
      "璃川出身",
      "朔溟出身",
      "秽渊出身"
    ],
    "domains": []
  },
  "profession": [],
  "ancestry": [
    {
      "id": "shenzhou-tiger-1.0-ancestry-xieling-trait1",
      "名称": "铸命之初",
      "种族": "械灵",
      "简介": "械灵为以灵石驱动的中型造化之体，形貌各异，体表映现灵光流转，机关缝隙中隐见阵纹微鸣。",
      "效果": "***铸命之初：*** 决定你是由谁创造以及为何目的而创造的。在创建角色时，选择一个最符合此目的的经历，永久获得 **+1** 加值。",
      "类别": 1
    },
    {
      "id": "shenzhou-tiger-1.0-ancestry-xieling-trait2",
      "名称": "律息重载",
      "种族": "械灵",
      "简介": "械灵为以灵石驱动的中型造化之体，形貌各异，体表映现灵光流转，机关缝隙中隐见阵纹微鸣。",
      "效果": "***律息重载：*** 当你进行短休时，你可以选择一个 **长休** 的休整行动代替 **短休** 的休整行动。",
      "类别": 2
    },
    {
      "id": "shenzhou-tiger-1.0-ancestry-longren-trait1",
      "名称": "鳞甲护体",
      "种族": "龙人",
      "简介": "龙人是具有东方龙特征的中型类人生物，身披青鳞玉甲，额生鹿角，鬃须飞扬，目光如电，气度自生威仪。",
      "效果": "***鳞甲护体：*** 你的鳞片提供天然保护。当你受到 **严重伤害** 时，你可以 **标记 1 压力点** 来少标记 **1 生命点**。",
      "类别": 1
    },
    {
      "id": "shenzhou-tiger-1.0-ancestry-longren-trait2",
      "名称": "吐元化威",
      "种族": "龙人",
      "简介": "龙人是具有东方龙特征的中型类人生物，身披青鳞玉甲，额生鹿角，鬃须飞扬，目光如电，气度自生威仪。",
      "效果": "***吐元化威：*** 选择一种元素作为你的吐息。你可以对 **邻近范围** 内的一个或一群目标使用此吐息，将其视为一种使用你的 **熟练值** 造成 **d8** 点 **魔法伤害** 的 **本能武器**。",
      "类别": 2
    },
    {
      "id": "shenzhou-tiger-1.0-ancestry-airen-trait1",
      "名称": "厚皮强骨",
      "种族": "矮人",
      "简介": "矮人是一种身形敦实的中型类人种族，臂粗拳厚，擅铸器营造，锤声响处，常有奇工巧物现世。",
      "效果": "***厚皮强骨：*** 当你受到 **轻度伤害** 时，你可以 **标记 2 压力点** 代替 **标记 1 生命点**。",
      "类别": 1
    },
    {
      "id": "shenzhou-tiger-1.0-ancestry-airen-trait2",
      "名称": "钢意难侵",
      "种族": "矮人",
      "简介": "矮人是一种身形敦实的中型类人种族，臂粗拳厚，擅铸器营造，锤声响处，常有奇工巧物现世。",
      "效果": "***钢意难侵：*** 花费 **3 希望点**，将受到的 **物理伤害** 减半。",
      "类别": 2
    },
    {
      "id": "shenzhou-tiger-1.0-ancestry-jingling-trait1",
      "名称": "应念即动",
      "种族": "精灵",
      "简介": "精灵是一种耳尖体轻的中型类人种族，眉眼清峻，天赋通灵，对天地灵息尤为敏感。",
      "效果": "***应念即动：*** **标记 1 压力点**，在 **反应掷骰** 上获得 **优势**。",
      "类别": 1
    },
    {
      "id": "shenzhou-tiger-1.0-ancestry-jingling-trait2",
      "名称": "灵冥静思",
      "种族": "精灵",
      "简介": "精灵是一种耳尖体轻的中型类人种族，眉眼清峻，天赋通灵，对天地灵息尤为敏感。",
      "效果": "***灵冥静思：*** 在休息期间，你可以进入冥想状态，选择一个 **额外** 的休整行动。",
      "类别": 2
    },
    {
      "id": "shenzhou-tiger-1.0-ancestry-yuling-trait1",
      "名称": "引息回翔",
      "种族": "羽灵",
      "简介": "羽灵是一种具有鸟类特征的小型类人生物，身覆彩羽，背生双翼，足为鸟爪。",
      "效果": "***引息回翔：*** 每场游戏一次，当你或 **邻近范围** 内一位自愿盟友完成动作掷骰后，你可花费 **3 希望点**，使其重新掷一次 **双生骰**。",
      "类别": 1
    },
    {
      "id": "shenzhou-tiger-1.0-ancestry-yuling-trait2",
      "名称": "御风展羽",
      "种族": "羽灵",
      "简介": "羽灵是一种具有鸟类特征的小型类人生物，身覆彩羽，背生双翼，足为鸟爪。",
      "效果": "***御风展羽：*** 你可以飞行。在飞行状态下，当你成为敌人攻击目标时，可 **标记 1 压力点**，在该次攻击中获得 **+2 加值** 以 **闪避**。",
      "类别": 2
    },
    {
      "id": "shenzhou-tiger-1.0-ancestry-huzu-trait1",
      "名称": "灵跃轻踪",
      "种族": "狐族",
      "简介": "狐族是一种具有狐狸特征的中型类人生物，生有蓬茸狐耳，尾长丰密，身形轻巧，眸带狡慧。",
      "效果": "***灵跃轻踪：*** 你可以像使用正常移动一样跳跃到 **邻近范围** 内的任何地方，让你轻松跳过障碍物、跨越缝隙或攀爬障碍。",
      "类别": 1
    },
    {
      "id": "shenzhou-tiger-1.0-ancestry-huzu-trait2",
      "名称": "尾击腾挪",
      "种族": "狐族",
      "简介": "狐族是一种具有狐狸特征的中型类人生物，生有蓬茸狐耳，尾长丰密，身形轻巧，眸带狡慧。",
      "效果": "***尾击腾挪：*** 当你对 **近战范围** 内的一个目标攻击成功时，你可以 **标记 1 压力点** 借力将自己推离目标，造成额外 **2d6 点伤害**，并将你自己或目标击退到 **邻近范围**。",
      "类别": 2
    },
    {
      "id": "shenzhou-tiger-1.0-ancestry-xiongmaoyi-trait1",
      "名称": "踏山破阵",
      "种族": "熊猫裔",
      "简介": "熊猫裔是一种具有熊猫特征的中型类人生物，肤毛黑白分明，眼圈浓墨如印，体宽掌厚，力大耐劳。",
      "效果": "***踏山破阵：*** 成功进行一次 **敏捷掷骰** 后，若你自 **远距离** 或 **极远距离** 突入目标 **近战范围**，可 **标记 1 压力点**，对所有 **近战范围** 内目标造成 **1d12 点物理伤害**。",
      "类别": 1
    },
    {
      "id": "shenzhou-tiger-1.0-ancestry-xiongmaoyi-trait2",
      "名称": "坚意如山",
      "种族": "熊猫裔",
      "简介": "熊猫裔是一种具有熊猫特征的中型类人生物，肤毛黑白分明，眼圈浓墨如印，体宽掌厚，力大耐劳。",
      "效果": "***坚意如山：*** 当你本应 **标记 1 压力点** 时，掷一个 **d6**。结果为 **6** 时，则无需标记。",
      "类别": 2
    },
    {
      "id": "shenzhou-tiger-1.0-ancestry-muling-trait1",
      "名称": "根络传心",
      "种族": "木灵",
      "简介": "木灵是一种类似人形的小型灵木生灵，通体由灵质木纹构成，肤如老树斑皮，身披枝芽苔斑。",
      "效果": "***根络传心：*** 进行一次 **本能掷骰 (12)**，与任何范围内的同族成员通过根络交换信息。",
      "类别": 1
    },
    {
      "id": "shenzhou-tiger-1.0-ancestry-muling-trait2",
      "名称": "余情寄叶",
      "种族": "木灵",
      "简介": "木灵是一种类似人形的小型灵木生灵，通体由灵质木纹构成，肤如老树斑皮，身披枝芽苔斑。",
      "效果": "***余情寄叶：*** 触摸一具最近死亡的尸体，你可以 **标记 1 压力点**，提取与某种情绪或感受相关的记忆。",
      "类别": 2
    },
    {
      "id": "shenzhou-tiger-1.0-ancestry-guiren-trait1",
      "名称": "灵壳庇身",
      "种族": "龟人",
      "简介": "龟族是一种具有乌龟特征的中型类人生物，背负厚甲，四肢粗短，其壳坚如磐石，亦常为占兆之器。",
      "效果": "***灵壳庇身：*** 你的 **伤害阈值** 获得等同于你 **熟练值** 的加值。",
      "类别": 1
    },
    {
      "id": "shenzhou-tiger-1.0-ancestry-guiren-trait2",
      "名称": "缩壳守静",
      "种族": "龟人",
      "简介": "龟族是一种具有乌龟特征的中型类人生物，背负厚甲，四肢粗短，其壳坚如磐石，亦常为占兆之器。",
      "效果": "***缩壳守静：*** **标记 1 压力点** 缩入龟壳，获得 **物理伤害抗性**，但 **动作掷骰** 有 **劣势**，且无法移动。",
      "类别": 2
    },
    {
      "id": "shenzhou-tiger-1.0-ancestry-juren-trait1",
      "名称": "躯伟命坚",
      "种族": "巨人",
      "简介": "巨人是一种体型魁伟的大型类人种族，筋骨嶙峋如铁石，行步如山岳挪移，气息自带威压。",
      "效果": "***躯伟命坚：*** 角色创建时，获得一个 **额外** 的 **生命槽**。",
      "类别": 1
    },
    {
      "id": "shenzhou-tiger-1.0-ancestry-juren-trait2",
      "名称": "巨臂横击",
      "种族": "巨人",
      "简介": "巨人是一种体型魁伟的大型类人种族，筋骨嶙峋如铁石，行步如山岳挪移，气息自带威压。",
      "效果": "***巨臂横击：*** 将任何 **近战范围** 的攻击或能力视为具有 **邻近范围**。",
      "类别": 2
    },
    {
      "id": "shenzhou-tiger-1.0-ancestry-diling-trait1",
      "名称": "游鳞无迹",
      "种族": "蛇人",
      "简介": "蛇人族是一种具有蛇特征的中型类人生物，下半身为强健修长的蛇尾，游走迅捷，静伏无声。",
      "效果": "***游鳞无迹：*** 你在 **敏捷掷骰** 中忽略 **劣势**。",
      "类别": 1
    },
    {
      "id": "shenzhou-tiger-1.0-ancestry-diling-trait2",
      "名称": "危觉本能",
      "种族": "蛇人",
      "简介": "蛇人族是一种具有蛇特征的中型类人生物，下半身为强健修长的蛇尾，游走迅捷，静伏无声。",
      "效果": "***危觉本能：*** 每次休息一次，**标记 1 压力点**，强制一个敌人重掷对你或 **邻近盟友** 的攻击。",
      "类别": 2
    },
    {
      "id": "shenzhou-tiger-1.0-ancestry-banshenren-trait1",
      "名称": "福缘同享",
      "种族": "半身人",
      "简介": "半身人是一种圆耳的小型类人种族，足掌宽厚覆毛，鼻嗅灵敏，能辨百味香辛与风中细语。",
      "效果": "***福缘同享：*** 每场游戏开始时，你队伍中的所有人皆获得 **1 希望点**。",
      "类别": 1
    },
    {
      "id": "shenzhou-tiger-1.0-ancestry-banshenren-trait2",
      "名称": "命途柔转",
      "种族": "半身人",
      "简介": "半身人是一种圆耳的小型类人种族，足掌宽厚覆毛，鼻嗅灵敏，能辨百味香辛与风中细语。",
      "效果": "***命途柔转：*** 当你掷出的 **希望骰** 结果为 **1** 时，你可以重掷该骰。",
      "类别": 2
    },
    {
      "id": "shenzhou-tiger-1.0-ancestry-renlei-trait1",
      "名称": "强志恒忍",
      "种族": "人类",
      "简介": "人类是一种圆耳直立的中型类人种族，五官端正，以灵巧双手与强大适应力著称，尤具坚韧耐性。",
      "效果": "***强志恒忍：*** 角色创建时获得一个 **额外** 的 **压力槽**。",
      "类别": 1
    },
    {
      "id": "shenzhou-tiger-1.0-ancestry-renlei-trait2",
      "名称": "适势应变",
      "种族": "人类",
      "简介": "人类是一种圆耳直立的中型类人种族，五官端正，以灵巧双手与强大适应力著称，尤具坚韧耐性。",
      "效果": "***适势应变：*** 当你在运用某个经历进行的掷骰失败时，你可以 **标记 1 压力点** 进行重掷。",
      "类别": 2
    },
    {
      "id": "shenzhou-tiger-1.0-ancestry-moyi-trait1",
      "名称": "逆命拒惧",
      "种族": "魔裔",
      "简介": "魔裔是一种具有混沌特征的中型类人生物，常见双角、尾刺、鳞痕与异瞳，气息炽烈诡异。",
      "效果": "***逆命拒惧：*** 当你掷出 **恐惧结果** 时，你可以 **标记 2 压力点**，将其改为掷出 **希望结果**。",
      "类别": 1
    },
    {
      "id": "shenzhou-tiger-1.0-ancestry-moyi-trait2",
      "名称": "凛目生威",
      "种族": "魔裔",
      "简介": "魔裔是一种具有混沌特征的中型类人生物，常见双角、尾刺、鳞痕与异瞳，气息炽烈诡异。",
      "效果": "***凛目生威：*** 你在恐吓敌意生物的掷骰中具有 **优势**。进行 **恐吓掷骰** 时具有 **优势**。",
      "类别": 2
    },
    {
      "id": "shenzhou-tiger-1.0-ancestry-huzu2-trait1",
      "名称": "静势凝身",
      "种族": "虎族",
      "简介": "虎族是一种具有老虎特征的中型类人生物，体覆斑纹，爪锋齿利，天生善于搏杀与追迹。",
      "效果": "***静势凝身：*** 当你进行 **敏捷掷骰** 时，你可以花费 **2 希望点** 来重掷你的 **希望骰**。",
      "类别": 1
    },
    {
      "id": "shenzhou-tiger-1.0-ancestry-huzu2-trait2",
      "名称": "猛爪破势",
      "种族": "虎族",
      "简介": "虎族是一种具有老虎特征的中型类人生物，体覆斑纹，爪锋齿利，天生善于搏杀与追迹。",
      "效果": "***猛爪破势：*** 进行一次 **敏捷掷骰** 来抓挠 **近战范围** 内的一个目标。成功时，目标暂时处于 *脆弱* 状态。",
      "类别": 2
    },
    {
      "id": "shenzhou-tiger-1.0-ancestry-liaozu-trait1",
      "名称": "残锋不倒",
      "种族": "獠族",
      "简介": "獠族是一种具有野猪特征的中型类人生物，獠牙外突，尤擅近战冲锋与野地求生。",
      "效果": "***残锋不倒：*** 当你剩余 **1 点生命值** 时，所有以你为目标的攻击掷骰具有 **劣势**。",
      "类别": 1
    },
    {
      "id": "shenzhou-tiger-1.0-ancestry-liaozu-trait2",
      "名称": "獠牙撕咬",
      "种族": "獠族",
      "简介": "獠族是一种具有野猪特征的中型类人生物，獠牙外突，尤擅近战冲锋与野地求生。",
      "效果": "***獠牙撕咬：*** 当你对 **近战范围** 内的一个目标攻击成功时，你可以花费 **1 希望点**，额外造成 **1d6 点伤害**。",
      "类别": 2
    },
    {
      "id": "shenzhou-tiger-1.0-ancestry-wayi-trait1",
      "名称": "水陆同行",
      "种族": "蛙裔",
      "简介": "蛙裔是一种具有青蛙特征的小型类人生物，肤薄湿润，指掌生蹼，能于陆泽之间自在穿行。",
      "效果": "***水陆同行：*** 你天生能够在水下呼吸和移动。",
      "类别": 1
    },
    {
      "id": "shenzhou-tiger-1.0-ancestry-wayi-trait2",
      "名称": "长舌缠击",
      "种族": "蛙裔",
      "简介": "蛙裔是一种具有青蛙特征的小型类人生物，肤薄湿润，指掌生蹼，能于陆泽之间自在穿行。",
      "效果": "***长舌缠击：*** 你可以使用你的长舌抓住 **近距离范围** 内的物体。**标记 1 压力点**，将你的舌头用作一把使用你的 **熟练值** 造成 **d12 物理伤害** 的 **灵巧近战武器**。",
      "类别": 2
    },
    {
      "id": "shenzhou-tiger-1.0-ancestry-yuanzu-trait1",
      "名称": "攀援如风",
      "种族": "猿族",
      "简介": "猿族是一种具猴猿特征的中型类人生物，四肢修长可握，善攀援跃跃，神态狡慧多变，机敏非常。",
      "效果": "***攀援如风：*** 你在涉及平衡和攀爬的 **敏捷掷骰** 中具有 **优势**。",
      "类别": 1
    },
    {
      "id": "shenzhou-tiger-1.0-ancestry-yuanzu-trait2",
      "名称": "身轻如跃",
      "种族": "猿族",
      "简介": "猿族是一种具猴猿特征的中型类人生物，四肢修长可握，善攀援跃跃，神态狡慧多变，机敏非常。",
      "效果": "***身轻如跃：*** 在创建角色时，**闪避值** 获得永久 **+1** 加值。",
      "类别": 2
    }
  ],
  "community": [
    {
      "id": "shenzhou-tiger-1.0-community-zhongzhou-origin",
      "名称": "中州出身",
      "特性": "皇权典章",
      "简介": "中州位于神州中央，地势平正，河网交织，四时运转有度。其都城昭明宫坐落于九川汇流之畔，宫署鳞次栉比，车马昼夜不歇。",
      "描述": "你可以花费 **2 希望点**，重新掷一次用于识别 **古器遗珍** 与 **史籍传闻**，或在 **城市街坊** 等地形中进行安全与危险判断的 **希望骰**。"
    },
    {
      "id": "shenzhou-tiger-1.0-community-cangling-origin",
      "名称": "苍岭出身",
      "特性": "术法根源",
      "简介": "苍岭位于神州东部，山林密布，云雾缭绕，古道曲折通幽。其都城衡书台建于高岭峡谷之间，高台俯瞰云涛，符光映照山壁。",
      "描述": "你可以花费 **2 希望点**，重新掷一次用于识别 **灵纹法器** 与 **术法余痕**，或在 **山林雾谷** 等地形中进行安全与危险判断的 **希望骰**。"
    },
    {
      "id": "shenzhou-tiger-1.0-community-danze-origin",
      "名称": "丹泽出身",
      "特性": "美学通感",
      "简介": "丹泽位于神州南部，水泽纵横，气候湿热，雾气终年不散。其都城绮罗楼建于泽心群岛之上，水榭浮桥交错，香灯映水通明。",
      "描述": "你可以花费 **2 希望点**，重新掷一次用于识别 **灵植妙药** 与 **民俗仪礼**，或在 **水泽流域** 等地形中进行安全与危险判断的 **希望骰**。"
    },
    {
      "id": "shenzhou-tiger-1.0-community-lichuan-origin",
      "名称": "璃川出身",
      "特性": "兵道战技",
      "简介": "璃川位于神州西部，丘岭连绵，赤岩遍地，风沙昼夜不断。其都城铸锋塔建于矿谷交汇之地，炉火长鸣不歇，锻声回荡山谷。",
      "描述": "你可以花费 **2 希望点**，重新掷一次用于识别 **金属砂石** 与 **构造机关**，或在 **丘陵矿壑** 等地形中进行安全与危险判断的 **希望骰**。"
    },
    {
      "id": "shenzhou-tiger-1.0-community-shuoming-origin",
      "名称": "朔溟出身",
      "特性": "御险狩猎",
      "简介": "朔溟位于神州北部，冰原广布，海崖凌峙，雪风终年不止。其都城玄霜阙建于温泉崖谷之间，泉气氤氲不散，楼阁温润如春。",
      "描述": "你可以花费 **2 希望点**，重新掷一次用于识别 **生物状态** 与 **魔物踪迹**，或在 **雪原冰湖** 等地形中进行安全与危险判断的 **希望骰**。"
    },
    {
      "id": "shenzhou-tiger-1.0-community-huiyuan-origin",
      "名称": "秽渊出身",
      "特性": "混沌勘破",
      "简介": "秽渊位于神州之外，秽气昼夜不散，地势翻覆如梦。既有断崖裂谷、黑水沼泽与浮空石林，亦不乏倒挂山峰、翻涌火海与永夜冰原。",
      "描述": "你可以花费 **2 希望点**，重新掷一次用于识别 **秽气残留** 与 **异常现象**，或在 **混沌畸变** 等地形中进行安全与危险判断的 **希望骰**。"
    }
  ],
  "subclass": [],
  "domain": [],
  "variant": []
}